cryptoutil/__init__.py
cryptoutil-0.0.2.dist-info/LICENSE
cryptoutil-0.0.2.dist-info/METADATA
cryptoutil-0.0.2.dist-info/WHEEL
cryptoutil-0.0.2.dist-info/top_level.txt
cryptoutil-0.0.2.dist-info/RECORD
