Metadata-Version: 2.1
Name: cryptoutil
Version: 0.0.2
Summary: A collection of cryptography related utilities.
Home-page: https://github.com/pooyavahidi/cryptoutil
Author: Pooya Vahidi
License: UNKNOWN
Platform: UNKNOWN
Classifier: Programming Language :: Python :: 3
Classifier: License :: OSI Approved :: MIT License
Classifier: Operating System :: OS Independent
Requires-Python: >=3.6
Requires-Dist: pybackpack (>=0.1.0)
Requires-Dist: cryptography (>=3.0.0)
